haystack_ml_stack/__init__.py
haystack_ml_stack/_serializers.py
haystack_ml_stack/app.py
haystack_ml_stack/cache.py
haystack_ml_stack/dynamo.py
haystack_ml_stack/exceptions.py
haystack_ml_stack/model_store.py
haystack_ml_stack/settings.py
haystack_ml_stack/utils.py
haystack_ml_stack/generated/__init__.py
haystack_ml_stack/generated/v1/__init__.py
haystack_ml_stack/generated/v1/features_pb2.py
haystack_ml_stack/generated/v1/features_pb2.pyi
haystack_ml_stack-0.3.4.dist-info/METADATA
haystack_ml_stack-0.3.4.dist-info/WHEEL
haystack_ml_stack-0.3.4.dist-info/top_level.txt
haystack_ml_stack-0.3.4.dist-info/RECORD
