Metadata-Version: 2.4
Name: haystack-ml-stack
Version: 0.3.4
Summary: Functions related to Haystack ML
Author-email: Oscar Vega <oscar@haystack.tv>
License: MIT
Requires-Python: >=3.11
Requires-Dist: protobuf==6.33.2
Provides-Extra: server
Requires-Dist: pydantic==2.5.0; extra == "server"
Requires-Dist: cachetools==5.5.2; extra == "server"
Requires-Dist: cloudpickle==2.2.1; extra == "server"
Requires-Dist: aioboto3==12.0.0; extra == "server"
Requires-Dist: fastapi==0.104.1; extra == "server"
Requires-Dist: pydantic-settings==2.2; extra == "server"
Requires-Dist: newrelic==11.1.0; extra == "server"
